local_databricks/__init__.py
local_databricks/exc.py
local_databricks/ldbutils/__init__.py
local_databricks/ldbutils/notebook.py
local_databricks/logger.py
local_databricks/session.py
local_databricks/settings.py
local_databricks-0.1.0.dist-info/LICENSE
local_databricks-0.1.0.dist-info/WHEEL
local_databricks-0.1.0.dist-info/METADATA
local_databricks-0.1.0.dist-info/RECORD
